req/__init__.py
req/req.py
bypass_req-0.0.2.dist-info/LICENSE.txt
bypass_req-0.0.2.dist-info/METADATA
bypass_req-0.0.2.dist-info/WHEEL
bypass_req-0.0.2.dist-info/top_level.txt
bypass_req-0.0.2.dist-info/RECORD
