Metadata-Version: 2.1
Name: bypass-req
Version: 0.0.2
Summary: HTTP library made for web protection
Home-page: UNKNOWN
Author: Sergej Zivkovic
Author-email: zivkovicsergej501@gmail.com
License: MIT
Download-URL: https://pypi.org/project/bypass-req/
Keywords: HTTP,Requests
Platform: UNKNOWN
Requires-Dist: sgrequests (==0.1.4)
